{"09nU4TW3wMZws3QlAjwoAA==":"inspiration-633x633.png","UeKMazJAMM4QT+w8FGAWxA==":"dth2700-12-g-696x464.jpeg","+A5KncrU1InaKq3xjMXTDg==":"background-633x633.png","6zFw6EDeM90YG6Ottdoh+A==":"front%20cover-982x1500.jpg","tctWMh9iHBgY322bNtI+uw==":"sexy%20pose-506x655.png","TBNGXdWnF+zqnKqomC02sg==":"pelisse-506x718.png","WBUFD+QG0xYfFELRQPXmMQ==":"seiiccubus-506x685.png","rC98jxWEHA104Q/EtmKQsg==":"keira-1784x2740.png","lTabkw6McCSFd8wLfjSDVA==":"gradient-3-1000x1000.png","PTSGVN14tV34SFXpo3Vzwg==":"vox-logo-animated.gif","Hm+9Gwrfmx7rACMi28tmfQ==":"tiled-background-2-1167x1167.png","SRJguyaIVH8MGCgE+PIbUA==":"tiled-background2-1167x1167.png","g0UBxCHg3O5ZXgvihuxJ2g==":"website-background2-1076x1076.png","DZKTkeP0BPjIv6MZMHMBRA==":"2020-03-16-21-39-42-window-794x1173.png","KOMPl4oJ2M2ART0m0OP54g==":"tracer-800x1131.png","IAaS4tDmbkgXl3LyKM3RYg==":"toastybox-small-1785x1264.png","jvYjlvycd18jSu/n9EqU3g==":"2021-02-24-10-23-58-window-1268x1274.png","vIC+Vu7GMe9yE7J1qQaADQ==":"creeper-bot-1536x2048.jpg","wMoYpzek4RneBvR27gRJtg==":"gum-1928x2338.png","865oXYyRD7Vbbw3oB8K4qw==":"2020-03-16%2022_07_33-window-644x585.png","hjB9A5MBWyrOvFU680HMgw==":"sprite-marina-644x636.png","79YkDCKalTFAJ3FEIlbGMg==":"sprite-beau-export-644x644.png","817Rsc/DUqzyr7Q/9+WHgA==":"wizards_tower_conversation.gif","ifjQz3fYRRDraVa5NZ7THA==":"haruko-shop-2-644x362.png","rcmTlu4dHhf0P2PPVKuS9w==":"mockup-geistburg-644x362.png","UyXTRGhJmDAdyGSFGZCITw==":"mockup-dreamgate.gif","+xpUr0iPXaAQC0PGdB4Msw==":"crumbleton-npcs.gif","9/REqVRohZIXflutMkLiHw==":"casino2-1.gif","K0zvdNaCn0yBeH+cdGuNeg==":"turn0001.gif","VZO5dZibEQYvbV4tnl76GQ==":"turn.gif","FJRX0fqeWI3QJEzIBQZaZQ==":"turn-1.gif","JM5OKvsUV0g89Y1Qe/f0cQ==":"turn-2.gif","bbPWBWHNj3sN78kBYd/kuw==":"turn-3.gif","y5geZBGHtrvuOuBofB3QtQ==":"turn-4.gif","VBiYYgwNYJQpCqVPZsTtfQ==":"turn-5.gif","1SpKEGPD+25f3wapoQps1A==":"shia-turn.gif","kFnm1vVjSuK87eavzpMsTg==":"turn0001-1.gif","39auxExU7S0ZNWRSaBvXYg==":"turnaround.gif","5sMNVkUgaJ8CLdYeoXv4ug==":"about-me.png","oJQdtKQ2bdLajZtjcIzUUA==":"background3.jpg","5Xkp9TAyY/hFbIHUlxTfeA==":"commissions-1974x1567.png","S2dAQBeDi4I/4d6zLrFbng==":"twitch-background.jpg","ja/N0Q4D+zW6htfrkvavcg==":"avatar-pixel2-768x768.png","fPlbS6MOrjGjYAYXv3vsRw==":"tiled-background-1167x1167.png","KY69VMcpSo4T1+3qn/rQSg==":"ezgif.com-gif-maker.gif","b2Q+gvwgMe3GPy6qPnKyLw==":"ezgif.com-gif-maker%20(8).gif","YfZ5BYkTqG5z2DL0kbaS7g==":"ezgif.com-gif-maker%20(10).gif","tcuWw3yiitSrVXmLQMuhPQ==":"ezgif.com-gif-maker%20(11).gif","mBxn/OxePBcBgikBpvg/SA==":"ezgif.com-gif-maker%20(12).gif","u62vZeD2GOGuuFMo2LxvLw==":"ezgif.com-gif-maker%20(13).gif","9MfQYhFLODQMcjVGcguE/Q==":"ezgif.com-gif-maker%20(9).gif","5qccq1410PNozlbWjR67jQ==":"ezgif.com-gif-maker%20(14).gif","ZbNlCbWYkkEIn6x14FIO7g==":"tiled-background2-2000x2000.png","Cesjxe6cW0NYFSAP4kiRig==":"features1.jpg","HUfpc9SvDwBk7sbVG2SgiA==":"features3.jpg","703jGkvtoXpxbZTG7S89UA==":"features2.jpg","WeIcOp+qLfFEPxVAXUUAEA==":"features4.jpg","YBOGpB2v5S1UimJCeYLHiA==":"ezgif.com-gif-maker%20(45).gif","9EGONPf8bSArLodGoRLaCQ==":"vox_owl-detailed-103022-506x572.png","actxaae/O0Q2cVLSQTyorg==":"commissions-1-1974x1567.png"}